{"appid":"16212869","developType":"normal","editor":{"curPath":"E:\\code\\baidu\\baidu_zhongyi\\pages\\index\\index.swan","expands":["E:\\code\\baidu\\baidu_zhongyi\\pages","E:\\code\\baidu\\baidu_zhongyi\\pages\\index","E:\\code\\baidu\\baidu_zhongyi\\pages\\detail"],"markdownUploadTimeMap":{},"paths":["E:\\code\\baidu\\baidu_zhongyi\\pages\\index\\index.css","E:\\code\\baidu\\baidu_zhongyi\\pages\\index\\index.js","E:\\code\\baidu\\baidu_zhongyi\\pages\\index\\index.swan","E:\\code\\baidu\\baidu_zhongyi\\pages\\index\\index.json","E:\\code\\baidu\\baidu_zhongyi\\pages\\detail\\detail.swan","E:\\code\\baidu\\baidu_zhongyi\\pages\\detail\\detail.js","E:\\code\\baidu\\baidu_zhongyi\\pages\\detail\\detail.css"],"recentlyFiles":["E:\\code\\baidu\\baidu_zhongyi\\pages\\index\\index.swan","E:\\code\\baidu\\baidu_zhongyi\\pages\\detail\\detail.swan","E:\\code\\baidu\\baidu_zhongyi\\pages\\detail\\detail.js","E:\\code\\baidu\\baidu_zhongyi\\pages\\detail\\detail.css","E:\\code\\baidu\\baidu_zhongyi\\pages\\index\\index.js","E:\\code\\baidu\\baidu_zhongyi\\pages\\index\\index.css","E:\\code\\baidu\\baidu_zhongyi\\pages\\index\\index.json","E:\\code\\baidu\\baidu_zhongyi\\pages\\detail\\detail.json","E:\\code\\baidu\\baidu_zhongyi\\app.js","E:\\code\\baidu\\baidu_zhongyi\\pkginfo.json","E:\\code\\baidu\\baidu_zhongyi\\app.json","E:\\code\\baidu\\baidu_zhongyi\\pages\\list\\list.js","E:\\code\\baidu\\baidu_huangjin\\pages\\index\\index.swan","E:\\code\\baidu\\baidu_huangjin\\pages\\detail\\detail.swan","E:\\code\\baidu\\baidu_huangjin\\pages\\index\\index.js","E:\\code\\baidu\\baidu_huangjin\\pages\\index\\index.css","E:\\code\\baidu\\baidu_huangjin\\pages\\template\\lunbo.swan","E:\\code\\baidu\\baidu_huangjin\\pages\\template\\list.swan","E:\\code\\baidu\\baidu_huangjin\\pages\\list\\list.swan","E:\\code\\baidu\\baidu_huangjin\\pages\\list\\list.js"]},"host":"baiduboxapp","preview":{"packageId":267914},"publish":{"hideTips":true,"version":"1.8"},"setting":{"urlCheck":true},"swan":{"baiduboxapp":{"extensionJsVersion":"1.4.0","swanJsVersion":"3.90.7"}}}